robusta/__init__.py
robusta/_version.py
robusta/api/__init__.py
robusta/clients/robusta_client.py
robusta/core/__init__.py
robusta/core/discovery/__init__.py
robusta/core/discovery/discovery.py
robusta/core/discovery/resource_names.py
robusta/core/discovery/top_service_resolver.py
robusta/core/discovery/utils.py
robusta/core/exceptions.py
robusta/core/model/__init__.py
robusta/core/model/base_params.py
robusta/core/model/cluster_status.py
robusta/core/model/env_vars.py
robusta/core/model/events.py
robusta/core/model/helm_release.py
robusta/core/model/jobs.py
robusta/core/model/k8s_operation_type.py
robusta/core/model/namespaces.py
robusta/core/model/nodes.py
robusta/core/model/openshift_group.py
robusta/core/model/pods.py
robusta/core/model/runner_config.py
robusta/core/model/services.py
robusta/core/persistency/__init__.py
robusta/core/persistency/in_memory.py
robusta/core/persistency/scheduled_jobs_states_dal.py
robusta/core/playbooks/__init__.py
robusta/core/playbooks/actions_registry.py
robusta/core/playbooks/base_trigger.py
robusta/core/playbooks/common.py
robusta/core/playbooks/container_playbook_utils.py
robusta/core/playbooks/crash_reporter.py
robusta/core/playbooks/generation.py
robusta/core/playbooks/internal/CRD_API_DOCUMENTATION.md
robusta/core/playbooks/internal/__init__.py
robusta/core/playbooks/internal/ai_integration.py
robusta/core/playbooks/internal/crds.py
robusta/core/playbooks/internal/discovery_events.py
robusta/core/playbooks/job_utils.py
robusta/core/playbooks/node_enrichment_utils.py
robusta/core/playbooks/node_playbook_utils.py
robusta/core/playbooks/oom_killer_utils.py
robusta/core/playbooks/playbook_utils.py
robusta/core/playbooks/playbooks_event_handler.py
robusta/core/playbooks/playbooks_event_handler_impl.py
robusta/core/playbooks/pod_utils/crashloop_utils.py
robusta/core/playbooks/pod_utils/imagepull_utils.py
robusta/core/playbooks/pod_utils/pending_pod_utils.py
robusta/core/playbooks/prometheus_enrichment_utils.py
robusta_api-0.31.4.dist-info/LICENSE
robusta_api-0.31.4.dist-info/METADATA
robusta_api-0.31.4.dist-info/WHEEL
robusta_api-0.31.4.dist-info/RECORD
