Metadata-Version: 2.1
Name: robusta-api
Version: 0.31.4
Summary: 
Author: Arik Alon
Author-email: arikalon1@users.noreply.github.com
Requires-Python: >=3.10,<3.12
Classifier: Programming Language :: Python :: 3
Classifier: Programming Language :: Python :: 3.10
Classifier: Programming Language :: Python :: 3.11
Provides-Extra: all
Requires-Dist: CairoSVG (>=2.5.2,<3.0.0) ; extra == "all"
Requires-Dist: Flask (>=3.0.0,<4.0.0) ; extra == "all"
Requires-Dist: apprise (==1.6.0)
Requires-Dist: attrs (>=23.1.0,<24.0.0)
Requires-Dist: better-exceptions (>=0.3.3,<0.4.0) ; extra == "all"
Requires-Dist: bitmath (>=1.3.3.1,<2.0.0.0)
Requires-Dist: boto3 (>=1.42.19,<2.0.0)
Requires-Dist: botocore (>=1.42.19,<2.0.0)
Requires-Dist: certifi (>=2023.7.22,<2024.0.0)
Requires-Dist: colorlog (>=5.0.1,<6.0.0)
Requires-Dist: croniter (>=1.3.15,<2.0.0)
Requires-Dist: cryptography (>=43.0.1,<44.0.0)
Requires-Dist: datadog-api-client (>=1.2.0,<2.0.0) ; extra == "all"
Requires-Dist: docutils (==0.19)
Requires-Dist: dpath (>=2.0.5,<3.0.0)
Requires-Dist: fpdf2 (>=2.7.1,<3.0.0)
Requires-Dist: grafana-api (>=1.0.3,<2.0.0) ; extra == "all"
Requires-Dist: h2 (>=4.3.0,<5.0.0)
Requires-Dist: hikaru-model-26 (>=1.1.1,<2.0.0)
Requires-Dist: httpx (==0.27.2)
Requires-Dist: humanize (>=3.13.1,<4.0.0)
Requires-Dist: idna (>=3.7)
Requires-Dist: jinja2 (>=3.1.5)
Requires-Dist: kafka-python (>=2.0.2,<3.0.0) ; extra == "all"
Requires-Dist: kubernetes (>=26.1.0,<27.0.0)
Requires-Dist: markdown2 (==2.4.13)
Requires-Dist: opsgenie-sdk (>=2.1.5,<3.0.0)
Requires-Dist: poetry-core (==1.1.0a7) ; extra == "all"
Requires-Dist: postgrest (==0.16.8)
Requires-Dist: prometheus-api-client (==0.5.4) ; extra == "all"
Requires-Dist: prometheus-client (>=0.12.0,<0.13.0)
Requires-Dist: prometrix (==0.2.9)
Requires-Dist: pydantic (>=1.8.1,<2.0.0)
Requires-Dist: pydash (==8.0.0)
Requires-Dist: pygal (>=3.0.0,<4.0.0)
Requires-Dist: pyjwt (>=2.4.0,<3.0.0)
Requires-Dist: pymsteams (>=0.1.16,<0.2.0)
Requires-Dist: pytz (>=2021.3,<2022.0)
Requires-Dist: pyyaml (>=6.0,<7.0)
Requires-Dist: regex (==2024.5.15)
Requires-Dist: requests (>=2.32.3,<3.0.0)
Requires-Dist: rocketchat-api (>=1.30.0,<2.0.0)
Requires-Dist: sentry-sdk[flask] (>=2.13.0,<3.0.0) ; extra == "all"
Requires-Dist: setuptools (>=80.9.0,<81.0.0)
Requires-Dist: slack-sdk (>=3.23.0,<4.0.0)
Requires-Dist: supabase (==2.5.1) ; extra == "all"
Requires-Dist: tabulate (>=0.8.10,<0.9.0) ; extra == "all"
Requires-Dist: toml (>=0.10.2,<0.11.0)
Requires-Dist: urllib3 (>=2.6.2,<3.0.0)
Requires-Dist: watchdog (>=2.1.0,<3.0.0) ; extra == "all"
Requires-Dist: watchgod (>=0.7,<0.8)
Requires-Dist: webexteamssdk (>=1.6.1,<2.0.0)
Requires-Dist: websocket-client (==1.3.3)
Requires-Dist: werkzeug (>=3.0.6)
